{
  "$schema": "https://vega.github.io/schema/vega-lite/v5.8.0.json",
  "config": {
    "view": {
      "continuousHeight": 300,
      "continuousWidth": 300
    }
  },
  "data": {
    "name": "data-3af4fe1d64ecf44ac751dc8bb97b7a0a"
  },
  "datasets": {
    "data-3af4fe1d64ecf44ac751dc8bb97b7a0a": [
      {
        "TSNE-1": -1.453866958618164,
        "TSNE-2": 1.569548487663269,
        "cluster": 3,
        "keywords": "economic, lower, disparity, higher, educational"
      },
      {
        "TSNE-1": -5.681116104125977,
        "TSNE-2": 5.087773323059082,
        "cluster": 3,
        "keywords": "economic, lower, disparity, higher, educational"
      },
      {
        "TSNE-1": 6.761875152587891,
        "TSNE-2": 1.151625633239746,
        "cluster": 2,
        "keywords": "least, factor, marriage, important, rate"
      },
      {
        "TSNE-1": -0.15502819418907166,
        "TSNE-2": -9.97331428527832,
        "cluster": 5,
        "keywords": "text, likely, may, marry, outside"
      },
      {
        "TSNE-1": 6.761875152587891,
        "TSNE-2": 1.151625633239746,
        "cluster": 2,
        "keywords": "least, factor, marriage, important, rate"
      },
      {
        "TSNE-1": -0.7565242648124695,
        "TSNE-2": 12.951308250427246,
        "cluster": 1,
        "keywords": "white, financial, stability, partner, tend"
      },
      {
        "TSNE-1": -1.0388855934143066,
        "TSNE-2": 6.925914287567139,
        "cluster": 1,
        "keywords": "white, financial, stability, partner, tend"
      },
      {
        "TSNE-1": 5.105773448944092,
        "TSNE-2": -2.164208173751831,
        "cluster": 0,
        "keywords": "black, woman, men, married, income"
      },
      {
        "TSNE-1": 1.8310085535049438,
        "TSNE-2": -8.084227561950684,
        "cluster": 0,
        "keywords": "black, woman, men, married, income"
      },
      {
        "TSNE-1": -13.74459457397461,
        "TSNE-2": -1.8071064949035645,
        "cluster": 4,
        "keywords": "passage, interracial, wealth, social, influence"
      },
      {
        "TSNE-1": 6.336849212646484,
        "TSNE-2": 7.666932106018066,
        "cluster": 1,
        "keywords": "white, financial, stability, partner, tend"
      },
      {
        "TSNE-1": -3.896528482437134,
        "TSNE-2": 10.388238906860352,
        "cluster": 1,
        "keywords": "white, financial, stability, partner, tend"
      },
      {
        "TSNE-1": -8.034313201904297,
        "TSNE-2": -1.5825856924057007,
        "cluster": 4,
        "keywords": "passage, interracial, wealth, social, influence"
      },
      {
        "TSNE-1": 9.902359008789062,
        "TSNE-2": -2.375835657119751,
        "cluster": 2,
        "keywords": "least, factor, marriage, important, rate"
      },
      {
        "TSNE-1": 0.9858426451683044,
        "TSNE-2": 4.559657573699951,
        "cluster": 1,
        "keywords": "white, financial, stability, partner, tend"
      },
      {
        "TSNE-1": 13.46990966796875,
        "TSNE-2": -4.65187931060791,
        "cluster": 2,
        "keywords": "least, factor, marriage, important, rate"
      },
      {
        "TSNE-1": -1.0388855934143066,
        "TSNE-2": 6.925914287567139,
        "cluster": 1,
        "keywords": "white, financial, stability, partner, tend"
      },
      {
        "TSNE-1": 0.334843248128891,
        "TSNE-2": 2.489793062210083,
        "cluster": 3,
        "keywords": "economic, lower, disparity, higher, educational"
      },
      {
        "TSNE-1": 1.1443041563034058,
        "TSNE-2": 0.7349295616149902,
        "cluster": 3,
        "keywords": "economic, lower, disparity, higher, educational"
      },
      {
        "TSNE-1": -0.21314966678619385,
        "TSNE-2": -13.807887077331543,
        "cluster": 5,
        "keywords": "text, likely, may, marry, outside"
      },
      {
        "TSNE-1": 7.288662910461426,
        "TSNE-2": -1.2991995811462402,
        "cluster": 2,
        "keywords": "least, factor, marriage, important, rate"
      },
      {
        "TSNE-1": -0.8581259250640869,
        "TSNE-2": -12.395273208618164,
        "cluster": 5,
        "keywords": "text, likely, may, marry, outside"
      },
      {
        "TSNE-1": -9.246150016784668,
        "TSNE-2": 2.7354156970977783,
        "cluster": 4,
        "keywords": "passage, interracial, wealth, social, influence"
      },
      {
        "TSNE-1": -0.9037147164344788,
        "TSNE-2": -0.477666437625885,
        "cluster": 3,
        "keywords": "economic, lower, disparity, higher, educational"
      },
      {
        "TSNE-1": -6.25116491317749,
        "TSNE-2": 7.8573808670043945,
        "cluster": 3,
        "keywords": "economic, lower, disparity, higher, educational"
      },
      {
        "TSNE-1": -1.3887709379196167,
        "TSNE-2": -10.054743766784668,
        "cluster": 5,
        "keywords": "text, likely, may, marry, outside"
      },
      {
        "TSNE-1": 6.737353801727295,
        "TSNE-2": -8.370203018188477,
        "cluster": 0,
        "keywords": "black, woman, men, married, income"
      },
      {
        "TSNE-1": -4.0253448486328125,
        "TSNE-2": -9.53579044342041,
        "cluster": 5,
        "keywords": "text, likely, may, marry, outside"
      },
      {
        "TSNE-1": 5.187317848205566,
        "TSNE-2": -9.67878246307373,
        "cluster": 0,
        "keywords": "black, woman, men, married, income"
      },
      {
        "TSNE-1": 5.12722635269165,
        "TSNE-2": -3.019002676010132,
        "cluster": 0,
        "keywords": "black, woman, men, married, income"
      },
      {
        "TSNE-1": 3.215744972229004,
        "TSNE-2": 1.781369924545288,
        "cluster": 2,
        "keywords": "least, factor, marriage, important, rate"
      },
      {
        "TSNE-1": -5.050485610961914,
        "TSNE-2": 8.646631240844727,
        "cluster": 1,
        "keywords": "white, financial, stability, partner, tend"
      },
      {
        "TSNE-1": -3.6216938495635986,
        "TSNE-2": 3.048982620239258,
        "cluster": 3,
        "keywords": "economic, lower, disparity, higher, educational"
      },
      {
        "TSNE-1": 10.829280853271484,
        "TSNE-2": 7.656569480895996,
        "cluster": 2,
        "keywords": "least, factor, marriage, important, rate"
      },
      {
        "TSNE-1": -1.0888569355010986,
        "TSNE-2": -4.514676094055176,
        "cluster": 0,
        "keywords": "black, woman, men, married, income"
      },
      {
        "TSNE-1": -4.506326675415039,
        "TSNE-2": -3.0945844650268555,
        "cluster": 3,
        "keywords": "economic, lower, disparity, higher, educational"
      },
      {
        "TSNE-1": -5.510801792144775,
        "TSNE-2": -6.320247650146484,
        "cluster": 5,
        "keywords": "text, likely, may, marry, outside"
      },
      {
        "TSNE-1": -5.952286720275879,
        "TSNE-2": 0.24424895644187927,
        "cluster": 3,
        "keywords": "economic, lower, disparity, higher, educational"
      },
      {
        "TSNE-1": -4.20924186706543,
        "TSNE-2": 0.1889791488647461,
        "cluster": 3,
        "keywords": "economic, lower, disparity, higher, educational"
      },
      {
        "TSNE-1": -6.999886512756348,
        "TSNE-2": 3.2451281547546387,
        "cluster": 3,
        "keywords": "economic, lower, disparity, higher, educational"
      },
      {
        "TSNE-1": -1.5448634624481201,
        "TSNE-2": 0.10460728406906128,
        "cluster": 3,
        "keywords": "economic, lower, disparity, higher, educational"
      },
      {
        "TSNE-1": -1.926451563835144,
        "TSNE-2": 9.583659172058105,
        "cluster": 1,
        "keywords": "white, financial, stability, partner, tend"
      },
      {
        "TSNE-1": 5.648160934448242,
        "TSNE-2": 3.5810365676879883,
        "cluster": 2,
        "keywords": "least, factor, marriage, important, rate"
      },
      {
        "TSNE-1": -2.4327898025512695,
        "TSNE-2": -4.634626865386963,
        "cluster": 0,
        "keywords": "black, woman, men, married, income"
      },
      {
        "TSNE-1": 13.58004093170166,
        "TSNE-2": 3.4898464679718018,
        "cluster": 2,
        "keywords": "least, factor, marriage, important, rate"
      },
      {
        "TSNE-1": 3.7121121883392334,
        "TSNE-2": -0.39752405881881714,
        "cluster": 0,
        "keywords": "black, woman, men, married, income"
      },
      {
        "TSNE-1": 1.6475110054016113,
        "TSNE-2": -8.753759384155273,
        "cluster": 0,
        "keywords": "black, woman, men, married, income"
      },
      {
        "TSNE-1": -13.74459457397461,
        "TSNE-2": -1.8071064949035645,
        "cluster": 4,
        "keywords": "passage, interracial, wealth, social, influence"
      },
      {
        "TSNE-1": -2.1039555072784424,
        "TSNE-2": -2.6433796882629395,
        "cluster": 3,
        "keywords": "economic, lower, disparity, higher, educational"
      },
      {
        "TSNE-1": -13.56771469116211,
        "TSNE-2": 0.8625389933586121,
        "cluster": 4,
        "keywords": "passage, interracial, wealth, social, influence"
      },
      {
        "TSNE-1": -0.0664915144443512,
        "TSNE-2": -7.715728759765625,
        "cluster": 0,
        "keywords": "black, woman, men, married, income"
      },
      {
        "TSNE-1": -3.5823581218719482,
        "TSNE-2": 9.275572776794434,
        "cluster": 1,
        "keywords": "white, financial, stability, partner, tend"
      },
      {
        "TSNE-1": 13.58004093170166,
        "TSNE-2": 3.4898464679718018,
        "cluster": 2,
        "keywords": "least, factor, marriage, important, rate"
      },
      {
        "TSNE-1": -1.0996606349945068,
        "TSNE-2": 3.182751417160034,
        "cluster": 3,
        "keywords": "economic, lower, disparity, higher, educational"
      },
      {
        "TSNE-1": 3.54217529296875,
        "TSNE-2": 11.632563591003418,
        "cluster": 1,
        "keywords": "white, financial, stability, partner, tend"
      },
      {
        "TSNE-1": 2.288943290710449,
        "TSNE-2": 5.869596004486084,
        "cluster": 1,
        "keywords": "white, financial, stability, partner, tend"
      },
      {
        "TSNE-1": -4.731603622436523,
        "TSNE-2": -11.681558609008789,
        "cluster": 5,
        "keywords": "text, likely, may, marry, outside"
      },
      {
        "TSNE-1": 1.042529582977295,
        "TSNE-2": -1.0030797719955444,
        "cluster": 0,
        "keywords": "black, woman, men, married, income"
      },
      {
        "TSNE-1": 9.756776809692383,
        "TSNE-2": 1.3618701696395874,
        "cluster": 2,
        "keywords": "least, factor, marriage, important, rate"
      },
      {
        "TSNE-1": -8.194581031799316,
        "TSNE-2": -8.860383987426758,
        "cluster": 5,
        "keywords": "text, likely, may, marry, outside"
      },
      {
        "TSNE-1": -10.072866439819336,
        "TSNE-2": -3.0476036071777344,
        "cluster": 4,
        "keywords": "passage, interracial, wealth, social, influence"
      },
      {
        "TSNE-1": 2.7419397830963135,
        "TSNE-2": 11.14245319366455,
        "cluster": 1,
        "keywords": "white, financial, stability, partner, tend"
      },
      {
        "TSNE-1": 3.215744972229004,
        "TSNE-2": 1.781369924545288,
        "cluster": 2,
        "keywords": "least, factor, marriage, important, rate"
      },
      {
        "TSNE-1": -0.03097131848335266,
        "TSNE-2": -4.434987545013428,
        "cluster": 0,
        "keywords": "black, woman, men, married, income"
      },
      {
        "TSNE-1": 1.137743353843689,
        "TSNE-2": 7.6661577224731445,
        "cluster": 1,
        "keywords": "white, financial, stability, partner, tend"
      },
      {
        "TSNE-1": 1.7814395427703857,
        "TSNE-2": -2.507533550262451,
        "cluster": 0,
        "keywords": "black, woman, men, married, income"
      },
      {
        "TSNE-1": -8.94841194152832,
        "TSNE-2": 5.581620216369629,
        "cluster": 3,
        "keywords": "economic, lower, disparity, higher, educational"
      },
      {
        "TSNE-1": -3.807128429412842,
        "TSNE-2": 5.838290214538574,
        "cluster": 3,
        "keywords": "economic, lower, disparity, higher, educational"
      },
      {
        "TSNE-1": 9.255202293395996,
        "TSNE-2": 0.47786611318588257,
        "cluster": 2,
        "keywords": "least, factor, marriage, important, rate"
      },
      {
        "TSNE-1": -5.376401424407959,
        "TSNE-2": 3.1150810718536377,
        "cluster": 3,
        "keywords": "economic, lower, disparity, higher, educational"
      },
      {
        "TSNE-1": 13.46990966796875,
        "TSNE-2": -4.65187931060791,
        "cluster": 2,
        "keywords": "least, factor, marriage, important, rate"
      },
      {
        "TSNE-1": 4.8172407150268555,
        "TSNE-2": -6.268117427825928,
        "cluster": 0,
        "keywords": "black, woman, men, married, income"
      },
      {
        "TSNE-1": -2.524671792984009,
        "TSNE-2": 4.094717025756836,
        "cluster": 3,
        "keywords": "economic, lower, disparity, higher, educational"
      },
      {
        "TSNE-1": -2.732469320297241,
        "TSNE-2": -1.4706746339797974,
        "cluster": 3,
        "keywords": "economic, lower, disparity, higher, educational"
      },
      {
        "TSNE-1": -2.780186176300049,
        "TSNE-2": -14.482176780700684,
        "cluster": 5,
        "keywords": "text, likely, may, marry, outside"
      },
      {
        "TSNE-1": 3.345120668411255,
        "TSNE-2": -3.4596707820892334,
        "cluster": 0,
        "keywords": "black, woman, men, married, income"
      },
      {
        "TSNE-1": 4.8172407150268555,
        "TSNE-2": -6.268117427825928,
        "cluster": 0,
        "keywords": "black, woman, men, married, income"
      },
      {
        "TSNE-1": -14.090921401977539,
        "TSNE-2": 2.09844708442688,
        "cluster": 4,
        "keywords": "passage, interracial, wealth, social, influence"
      },
      {
        "TSNE-1": -7.317150115966797,
        "TSNE-2": -6.064134120941162,
        "cluster": 5,
        "keywords": "text, likely, may, marry, outside"
      },
      {
        "TSNE-1": -8.607666015625,
        "TSNE-2": 2.2215521335601807,
        "cluster": 4,
        "keywords": "passage, interracial, wealth, social, influence"
      },
      {
        "TSNE-1": 6.336849212646484,
        "TSNE-2": 7.666932106018066,
        "cluster": 1,
        "keywords": "white, financial, stability, partner, tend"
      },
      {
        "TSNE-1": -8.194581031799316,
        "TSNE-2": -8.860383987426758,
        "cluster": 5,
        "keywords": "text, likely, may, marry, outside"
      },
      {
        "TSNE-1": -3.3542237281799316,
        "TSNE-2": 1.5820732116699219,
        "cluster": 3,
        "keywords": "economic, lower, disparity, higher, educational"
      },
      {
        "TSNE-1": -4.20924186706543,
        "TSNE-2": 0.1889791488647461,
        "cluster": 3,
        "keywords": "economic, lower, disparity, higher, educational"
      },
      {
        "TSNE-1": -4.134443759918213,
        "TSNE-2": -10.698624610900879,
        "cluster": 5,
        "keywords": "text, likely, may, marry, outside"
      },
      {
        "TSNE-1": 7.224112033843994,
        "TSNE-2": 6.196387767791748,
        "cluster": 2,
        "keywords": "least, factor, marriage, important, rate"
      },
      {
        "TSNE-1": -8.412956237792969,
        "TSNE-2": -5.76967716217041,
        "cluster": 4,
        "keywords": "passage, interracial, wealth, social, influence"
      },
      {
        "TSNE-1": -0.6983331441879272,
        "TSNE-2": 4.4088969230651855,
        "cluster": 3,
        "keywords": "economic, lower, disparity, higher, educational"
      },
      {
        "TSNE-1": 10.422510147094727,
        "TSNE-2": 6.7735066413879395,
        "cluster": 2,
        "keywords": "least, factor, marriage, important, rate"
      },
      {
        "TSNE-1": -2.792410135269165,
        "TSNE-2": 7.032843112945557,
        "cluster": 1,
        "keywords": "white, financial, stability, partner, tend"
      },
      {
        "TSNE-1": 3.215744972229004,
        "TSNE-2": 1.781369924545288,
        "cluster": 2,
        "keywords": "least, factor, marriage, important, rate"
      },
      {
        "TSNE-1": 7.26462984085083,
        "TSNE-2": -5.051884174346924,
        "cluster": 0,
        "keywords": "black, woman, men, married, income"
      }
    ]
  },
  "encoding": {
    "color": {
      "field": "keywords",
      "legend": {
        "title": "Keywords"
      },
      "type": "nominal"
    },
    "tooltip": [
      {
        "field": "keywords",
        "type": "nominal"
      }
    ],
    "x": {
      "field": "TSNE-1",
      "type": "quantitative"
    },
    "y": {
      "field": "TSNE-2",
      "type": "quantitative"
    }
  },
  "mark": {
    "size": 60,
    "type": "circle"
  },
  "params": [
    {
      "bind": "scales",
      "name": "param_34",
      "select": {
        "encodings": [
          "x",
          "y"
        ],
        "type": "interval"
      }
    }
  ],
  "title": {
    "align": "center",
    "text": "2024-26688 - does income factor into black women marrying white men"
  }
}