{
  "$schema": "https://vega.github.io/schema/vega-lite/v5.8.0.json",
  "config": {
    "view": {
      "continuousHeight": 300,
      "continuousWidth": 300
    }
  },
  "data": {
    "name": "data-b8b98e47be38e8887c31222eb679d3bb"
  },
  "datasets": {
    "data-b8b98e47be38e8887c31222eb679d3bb": [
      {
        "TSNE-1": -5.07635498046875,
        "TSNE-2": 1.7533996105194092,
        "cluster": 0,
        "keywords": "individual, good, positive, proactive, high"
      },
      {
        "TSNE-1": -10.46957015991211,
        "TSNE-2": 2.622316837310791,
        "cluster": 0,
        "keywords": "individual, good, positive, proactive, high"
      },
      {
        "TSNE-1": 0.09680071473121643,
        "TSNE-2": -7.946142196655273,
        "cluster": 2,
        "keywords": "time, difficult, life, decision, better"
      },
      {
        "TSNE-1": 2.471163749694824,
        "TSNE-2": -0.847345232963562,
        "cluster": 1,
        "keywords": "ask, help, able, overcome, situation"
      },
      {
        "TSNE-1": 0.09680071473121643,
        "TSNE-2": -7.946142196655273,
        "cluster": 2,
        "keywords": "time, difficult, life, decision, better"
      },
      {
        "TSNE-1": 3.992027759552002,
        "TSNE-2": 6.305350303649902,
        "cluster": 3,
        "keywords": "face, hiding, sense, instead, challenge"
      },
      {
        "TSNE-1": 7.042782306671143,
        "TSNE-2": -4.482685089111328,
        "cluster": 5,
        "keywords": "experience, remind, hide, accept, quality"
      },
      {
        "TSNE-1": -3.1610240936279297,
        "TSNE-2": 4.775075435638428,
        "cluster": 0,
        "keywords": "individual, good, positive, proactive, high"
      },
      {
        "TSNE-1": -0.0296328105032444,
        "TSNE-2": -5.032528400421143,
        "cluster": 2,
        "keywords": "time, difficult, life, decision, better"
      },
      {
        "TSNE-1": 7.705074310302734,
        "TSNE-2": 6.14987850189209,
        "cluster": 3,
        "keywords": "face, hiding, sense, instead, challenge"
      },
      {
        "TSNE-1": -2.8442325592041016,
        "TSNE-2": -15.311834335327148,
        "cluster": 2,
        "keywords": "time, difficult, life, decision, better"
      },
      {
        "TSNE-1": -3.6566715240478516,
        "TSNE-2": -8.33657455444336,
        "cluster": 2,
        "keywords": "time, difficult, life, decision, better"
      },
      {
        "TSNE-1": -6.777288913726807,
        "TSNE-2": 4.967381000518799,
        "cluster": 0,
        "keywords": "individual, good, positive, proactive, high"
      },
      {
        "TSNE-1": 7.998780727386475,
        "TSNE-2": -7.950475692749023,
        "cluster": 5,
        "keywords": "experience, remind, hide, accept, quality"
      },
      {
        "TSNE-1": 10.510364532470703,
        "TSNE-2": 5.821805000305176,
        "cluster": 3,
        "keywords": "face, hiding, sense, instead, challenge"
      },
      {
        "TSNE-1": -6.379415988922119,
        "TSNE-2": 7.822400093078613,
        "cluster": 0,
        "keywords": "individual, good, positive, proactive, high"
      },
      {
        "TSNE-1": 12.133628845214844,
        "TSNE-2": -3.9494142532348633,
        "cluster": 5,
        "keywords": "experience, remind, hide, accept, quality"
      },
      {
        "TSNE-1": -3.1610240936279297,
        "TSNE-2": 4.775075435638428,
        "cluster": 0,
        "keywords": "individual, good, positive, proactive, high"
      },
      {
        "TSNE-1": -4.655183792114258,
        "TSNE-2": 9.688170433044434,
        "cluster": 0,
        "keywords": "individual, good, positive, proactive, high"
      },
      {
        "TSNE-1": -0.5408795475959778,
        "TSNE-2": 10.343791961669922,
        "cluster": 0,
        "keywords": "individual, good, positive, proactive, high"
      },
      {
        "TSNE-1": 4.153305530548096,
        "TSNE-2": -0.07685999572277069,
        "cluster": 1,
        "keywords": "ask, help, able, overcome, situation"
      },
      {
        "TSNE-1": -5.560599327087402,
        "TSNE-2": -3.4262757301330566,
        "cluster": 4,
        "keywords": "confidence, likely, emotional, resilience, rather"
      },
      {
        "TSNE-1": 4.153305530548096,
        "TSNE-2": -0.07685999572277069,
        "cluster": 1,
        "keywords": "ask, help, able, overcome, situation"
      },
      {
        "TSNE-1": -3.0050904750823975,
        "TSNE-2": 1.2917572259902954,
        "cluster": 0,
        "keywords": "individual, good, positive, proactive, high"
      },
      {
        "TSNE-1": -2.2481486797332764,
        "TSNE-2": -0.30465006828308105,
        "cluster": 1,
        "keywords": "ask, help, able, overcome, situation"
      },
      {
        "TSNE-1": -6.683551788330078,
        "TSNE-2": 1.4205694198608398,
        "cluster": 0,
        "keywords": "individual, good, positive, proactive, high"
      },
      {
        "TSNE-1": 4.716152667999268,
        "TSNE-2": -2.378998279571533,
        "cluster": 1,
        "keywords": "ask, help, able, overcome, situation"
      },
      {
        "TSNE-1": 10.130369186401367,
        "TSNE-2": 3.1872591972351074,
        "cluster": 3,
        "keywords": "face, hiding, sense, instead, challenge"
      },
      {
        "TSNE-1": 10.532368659973145,
        "TSNE-2": 5.129990577697754,
        "cluster": 3,
        "keywords": "face, hiding, sense, instead, challenge"
      },
      {
        "TSNE-1": 2.0057787895202637,
        "TSNE-2": -2.603822946548462,
        "cluster": 1,
        "keywords": "ask, help, able, overcome, situation"
      },
      {
        "TSNE-1": 0.7922317981719971,
        "TSNE-2": -5.134270668029785,
        "cluster": 2,
        "keywords": "time, difficult, life, decision, better"
      },
      {
        "TSNE-1": -10.139771461486816,
        "TSNE-2": -8.045649528503418,
        "cluster": 4,
        "keywords": "confidence, likely, emotional, resilience, rather"
      },
      {
        "TSNE-1": -6.059374809265137,
        "TSNE-2": 2.887319564819336,
        "cluster": 0,
        "keywords": "individual, good, positive, proactive, high"
      },
      {
        "TSNE-1": -7.559695243835449,
        "TSNE-2": -2.8493967056274414,
        "cluster": 4,
        "keywords": "confidence, likely, emotional, resilience, rather"
      },
      {
        "TSNE-1": -4.808136463165283,
        "TSNE-2": 5.662528991699219,
        "cluster": 0,
        "keywords": "individual, good, positive, proactive, high"
      },
      {
        "TSNE-1": 2.212334394454956,
        "TSNE-2": -8.225591659545898,
        "cluster": 2,
        "keywords": "time, difficult, life, decision, better"
      },
      {
        "TSNE-1": -12.970330238342285,
        "TSNE-2": 0.2746068239212036,
        "cluster": 4,
        "keywords": "confidence, likely, emotional, resilience, rather"
      },
      {
        "TSNE-1": -1.1760207414627075,
        "TSNE-2": -2.4290480613708496,
        "cluster": 1,
        "keywords": "ask, help, able, overcome, situation"
      },
      {
        "TSNE-1": 7.698205947875977,
        "TSNE-2": 2.111962080001831,
        "cluster": 3,
        "keywords": "face, hiding, sense, instead, challenge"
      },
      {
        "TSNE-1": -7.619515419006348,
        "TSNE-2": -0.8924487829208374,
        "cluster": 4,
        "keywords": "confidence, likely, emotional, resilience, rather"
      },
      {
        "TSNE-1": -9.63813304901123,
        "TSNE-2": 6.257040977478027,
        "cluster": 0,
        "keywords": "individual, good, positive, proactive, high"
      },
      {
        "TSNE-1": -3.941243886947632,
        "TSNE-2": -2.8814775943756104,
        "cluster": 4,
        "keywords": "confidence, likely, emotional, resilience, rather"
      },
      {
        "TSNE-1": -5.165172576904297,
        "TSNE-2": 0.3708238899707794,
        "cluster": 0,
        "keywords": "individual, good, positive, proactive, high"
      },
      {
        "TSNE-1": 5.4227986335754395,
        "TSNE-2": -5.747512340545654,
        "cluster": 5,
        "keywords": "experience, remind, hide, accept, quality"
      },
      {
        "TSNE-1": 4.2566094398498535,
        "TSNE-2": -9.909202575683594,
        "cluster": 2,
        "keywords": "time, difficult, life, decision, better"
      },
      {
        "TSNE-1": 13.665992736816406,
        "TSNE-2": -0.27421239018440247,
        "cluster": 5,
        "keywords": "experience, remind, hide, accept, quality"
      },
      {
        "TSNE-1": -11.08859634399414,
        "TSNE-2": -6.295615196228027,
        "cluster": 4,
        "keywords": "confidence, likely, emotional, resilience, rather"
      },
      {
        "TSNE-1": 9.451178550720215,
        "TSNE-2": 9.264543533325195,
        "cluster": 3,
        "keywords": "face, hiding, sense, instead, challenge"
      },
      {
        "TSNE-1": -2.8442325592041016,
        "TSNE-2": -15.311834335327148,
        "cluster": 2,
        "keywords": "time, difficult, life, decision, better"
      },
      {
        "TSNE-1": 3.434083938598633,
        "TSNE-2": -9.381855964660645,
        "cluster": 2,
        "keywords": "time, difficult, life, decision, better"
      },
      {
        "TSNE-1": -0.18728019297122955,
        "TSNE-2": 2.793466567993164,
        "cluster": 1,
        "keywords": "ask, help, able, overcome, situation"
      },
      {
        "TSNE-1": 8.024419784545898,
        "TSNE-2": 7.069263935089111,
        "cluster": 3,
        "keywords": "face, hiding, sense, instead, challenge"
      },
      {
        "TSNE-1": -6.827675819396973,
        "TSNE-2": 3.816880464553833,
        "cluster": 0,
        "keywords": "individual, good, positive, proactive, high"
      },
      {
        "TSNE-1": 13.665992736816406,
        "TSNE-2": -0.27421239018440247,
        "cluster": 5,
        "keywords": "experience, remind, hide, accept, quality"
      },
      {
        "TSNE-1": -8.95438289642334,
        "TSNE-2": 3.820875406265259,
        "cluster": 0,
        "keywords": "individual, good, positive, proactive, high"
      },
      {
        "TSNE-1": 2.6481587886810303,
        "TSNE-2": 1.9264384508132935,
        "cluster": 1,
        "keywords": "ask, help, able, overcome, situation"
      },
      {
        "TSNE-1": -4.667043209075928,
        "TSNE-2": 8.489875793457031,
        "cluster": 0,
        "keywords": "individual, good, positive, proactive, high"
      },
      {
        "TSNE-1": 11.91268539428711,
        "TSNE-2": 7.72787618637085,
        "cluster": 3,
        "keywords": "face, hiding, sense, instead, challenge"
      },
      {
        "TSNE-1": 0.15224352478981018,
        "TSNE-2": -10.800185203552246,
        "cluster": 2,
        "keywords": "time, difficult, life, decision, better"
      },
      {
        "TSNE-1": 4.981831073760986,
        "TSNE-2": 1.9886924028396606,
        "cluster": 1,
        "keywords": "ask, help, able, overcome, situation"
      },
      {
        "TSNE-1": 4.5286126136779785,
        "TSNE-2": 3.384343147277832,
        "cluster": 1,
        "keywords": "ask, help, able, overcome, situation"
      },
      {
        "TSNE-1": 0.42667508125305176,
        "TSNE-2": 7.113008975982666,
        "cluster": 1,
        "keywords": "ask, help, able, overcome, situation"
      },
      {
        "TSNE-1": 6.860337734222412,
        "TSNE-2": -1.836260199546814,
        "cluster": 5,
        "keywords": "experience, remind, hide, accept, quality"
      },
      {
        "TSNE-1": -8.372593879699707,
        "TSNE-2": -4.802971363067627,
        "cluster": 4,
        "keywords": "confidence, likely, emotional, resilience, rather"
      },
      {
        "TSNE-1": -11.700727462768555,
        "TSNE-2": -0.42272892594337463,
        "cluster": 4,
        "keywords": "confidence, likely, emotional, resilience, rather"
      },
      {
        "TSNE-1": -11.826981544494629,
        "TSNE-2": 4.114784240722656,
        "cluster": 0,
        "keywords": "individual, good, positive, proactive, high"
      },
      {
        "TSNE-1": -11.236644744873047,
        "TSNE-2": -1.9929572343826294,
        "cluster": 4,
        "keywords": "confidence, likely, emotional, resilience, rather"
      },
      {
        "TSNE-1": -9.432767868041992,
        "TSNE-2": 0.9496123790740967,
        "cluster": 4,
        "keywords": "confidence, likely, emotional, resilience, rather"
      },
      {
        "TSNE-1": -0.013357268646359444,
        "TSNE-2": 0.9679990410804749,
        "cluster": 1,
        "keywords": "ask, help, able, overcome, situation"
      },
      {
        "TSNE-1": 2.8642008304595947,
        "TSNE-2": 0.45379212498664856,
        "cluster": 1,
        "keywords": "ask, help, able, overcome, situation"
      },
      {
        "TSNE-1": 0.637674868106842,
        "TSNE-2": -0.47168052196502686,
        "cluster": 1,
        "keywords": "ask, help, able, overcome, situation"
      },
      {
        "TSNE-1": 11.832892417907715,
        "TSNE-2": -4.403872013092041,
        "cluster": 5,
        "keywords": "experience, remind, hide, accept, quality"
      },
      {
        "TSNE-1": 3.172036647796631,
        "TSNE-2": -4.110818862915039,
        "cluster": 1,
        "keywords": "ask, help, able, overcome, situation"
      },
      {
        "TSNE-1": -2.2400319576263428,
        "TSNE-2": -11.301769256591797,
        "cluster": 2,
        "keywords": "time, difficult, life, decision, better"
      },
      {
        "TSNE-1": -4.690341949462891,
        "TSNE-2": -5.552783966064453,
        "cluster": 4,
        "keywords": "confidence, likely, emotional, resilience, rather"
      },
      {
        "TSNE-1": -14.500333786010742,
        "TSNE-2": 1.002216100692749,
        "cluster": 4,
        "keywords": "confidence, likely, emotional, resilience, rather"
      },
      {
        "TSNE-1": 9.263008117675781,
        "TSNE-2": -0.9576209783554077,
        "cluster": 5,
        "keywords": "experience, remind, hide, accept, quality"
      },
      {
        "TSNE-1": 3.172036647796631,
        "TSNE-2": -4.110818862915039,
        "cluster": 1,
        "keywords": "ask, help, able, overcome, situation"
      },
      {
        "TSNE-1": 1.0210039615631104,
        "TSNE-2": 6.135302543640137,
        "cluster": 1,
        "keywords": "ask, help, able, overcome, situation"
      },
      {
        "TSNE-1": 9.927978515625,
        "TSNE-2": 7.8587188720703125,
        "cluster": 3,
        "keywords": "face, hiding, sense, instead, challenge"
      },
      {
        "TSNE-1": -8.13620662689209,
        "TSNE-2": 1.360200047492981,
        "cluster": 0,
        "keywords": "individual, good, positive, proactive, high"
      },
      {
        "TSNE-1": -3.6566715240478516,
        "TSNE-2": -8.33657455444336,
        "cluster": 2,
        "keywords": "time, difficult, life, decision, better"
      },
      {
        "TSNE-1": 4.895746231079102,
        "TSNE-2": 4.297914981842041,
        "cluster": 1,
        "keywords": "ask, help, able, overcome, situation"
      },
      {
        "TSNE-1": -3.3133819103240967,
        "TSNE-2": -0.9739155769348145,
        "cluster": 1,
        "keywords": "ask, help, able, overcome, situation"
      },
      {
        "TSNE-1": -7.619515419006348,
        "TSNE-2": -0.8924487829208374,
        "cluster": 4,
        "keywords": "confidence, likely, emotional, resilience, rather"
      },
      {
        "TSNE-1": 11.961782455444336,
        "TSNE-2": 5.522043228149414,
        "cluster": 3,
        "keywords": "face, hiding, sense, instead, challenge"
      },
      {
        "TSNE-1": -1.2824199199676514,
        "TSNE-2": -5.314303398132324,
        "cluster": 2,
        "keywords": "time, difficult, life, decision, better"
      },
      {
        "TSNE-1": 1.961766004562378,
        "TSNE-2": 3.33858323097229,
        "cluster": 1,
        "keywords": "ask, help, able, overcome, situation"
      },
      {
        "TSNE-1": -7.912469863891602,
        "TSNE-2": 8.362137794494629,
        "cluster": 0,
        "keywords": "individual, good, positive, proactive, high"
      },
      {
        "TSNE-1": -5.00693416595459,
        "TSNE-2": -10.689468383789062,
        "cluster": 2,
        "keywords": "time, difficult, life, decision, better"
      },
      {
        "TSNE-1": -3.8978350162506104,
        "TSNE-2": 3.0554513931274414,
        "cluster": 0,
        "keywords": "individual, good, positive, proactive, high"
      },
      {
        "TSNE-1": -10.139771461486816,
        "TSNE-2": -8.045649528503418,
        "cluster": 4,
        "keywords": "confidence, likely, emotional, resilience, rather"
      },
      {
        "TSNE-1": 5.598167896270752,
        "TSNE-2": -0.3503991961479187,
        "cluster": 1,
        "keywords": "ask, help, able, overcome, situation"
      }
    ]
  },
  "encoding": {
    "color": {
      "field": "keywords",
      "legend": {
        "title": "Keywords"
      },
      "type": "nominal"
    },
    "tooltip": [
      {
        "field": "keywords",
        "type": "nominal"
      }
    ],
    "x": {
      "field": "TSNE-1",
      "type": "quantitative"
    },
    "y": {
      "field": "TSNE-2",
      "type": "quantitative"
    }
  },
  "mark": {
    "size": 60,
    "type": "circle"
  },
  "params": [
    {
      "bind": "scales",
      "name": "param_278",
      "select": {
        "encodings": [
          "x",
          "y"
        ],
        "type": "interval"
      }
    }
  ],
  "title": {
    "align": "center",
    "text": "2024-33513 - how can good self-esteem help you through difficult situations?"
  }
}